Workbook

Sheet sheet jan
A1: --- Sheet Jan --- | J1: TASK 6 | L1: FROM SHEET 2 TO SHEET 11
A2: Product | B2: Sales | J2: CONSOLIDATE DATA
A3: Pen | B3: 2000
A4: Book | B4: 3500
A5: Bag | B5: 5000

Sheet sheet feb
A1: --- Sheet Feb ---
A2: Product | B2: Sales
A3: Pen | B3: 2500
A4: Book | B4: 3000
A5: Bag | B5: 4500

Sheet sheet mar
A1: --- Sheet Mar ---
A2: Product | B2: Sales
A3: Pen | B3: 3000
A4: Book | B4: 4000
A5: Bag | B5: 6000

Sheet total
C1: Sales
B2: Task_6_Consolidate | C2: ='sheet feb'!$B$3 -> 2500
B3: Task_6_Consolidate | C3: ='sheet jan'!$B$3 -> 2000
B4: Task_6_Consolidate | C4: ='sheet mar'!$B$3 -> 3000
A5: Pen | C5: =SUM(C2:C4) -> 7500
B6: Task_6_Consolidate | C6: ='sheet feb'!$B$4 -> 3000
B7: Task_6_Consolidate | C7: ='sheet jan'!$B$4 -> 3500
B8: Task_6_Consolidate | C8: ='sheet mar'!$B$4 -> 4000
A9: Book | C9: =SUM(C6:C8) -> 10500
B10: Task_6_Consolidate | C10: ='sheet feb'!$B$5 -> 4500
B11: Task_6_Consolidate | C11: ='sheet jan'!$B$5 -> 5000
B12: Task_6_Consolidate | C12: ='sheet mar'!$B$5 -> 6000
A13: Bag | C13: =SUM(C10:C12) -> 15500

Sheet store1
A1: --- Sheet Store1 ---
A2: Item | B2: Sales
A3: Laptop | B3: 50
A4: Mobile | B4: 80
A5: TV | B5: 40

Sheet store2
A1: --- Sheet Store2 ---
A2: Item | B2: Sales
A3: Laptop | B3: 60
A4: Mobile | B4: 70
A5: TV | B5: 50

Sheet store3
C1: Sales
B2: Task_6_Consolidate | C2: =store1!$B$3 -> 50
B3: Task_6_Consolidate | C3: =store2!$B$3 -> 60
A4: Laptop | C4: =SUM(C2:C3) -> 110
B5: Task_6_Consolidate | C5: =store1!$B$4 -> 80
B6: Task_6_Consolidate | C6: =store2!$B$4 -> 70
A7: Mobile | C7: =SUM(C5:C6) -> 150
B8: Task_6_Consolidate | C8: =store1!$B$5 -> 40
B9: Task_6_Consolidate | C9: =store2!$B$5 -> 50
A10: TV | C10: =SUM(C8:C9) -> 90

Sheet q1budget
A1: --- Sheet Q1 ---
A2: Category | B2: Amount
A3: Rent | B3: 20000
A4: Salary | B4: 80000
A5: Internet | B5: 5000

Sheet q2budget
A1: --- Sheet Q2 ---
A2: Category | B2: Amount
A3: Salary | B3: 85000
A4: Internet | B4: 6000
A5: Rent | B5: 21000

Sheet q3budget
C1: Amount
B2: Task_6_Consolidate | C2: =q1budget!$B$3 -> 20000
B3: Task_6_Consolidate | C3: =q2budget!$B$5 -> 21000
A4: Rent | C4: =SUM(C2:C3) -> 41000
B5: Task_6_Consolidate | C5: =q1budget!$B$4 -> 80000
B6: Task_6_Consolidate | C6: =q2budget!$B$3 -> 85000
A7: Salary | C7: =SUM(C5:C6) -> 165000
B8: Task_6_Consolidate | C8: =q1budget!$B$5 -> 5000
B9: Task_6_Consolidate | C9: =q2budget!$B$4 -> 6000
A10: Internet | C10: =SUM(C8:C9) -> 11000

Sheet sectionA
A1: --- Section A ---
A2: Name | B2: Marks
A3: Ravi | B3: 78
A4: Priya | B4: 85
A5: Karan | B5: 90

Sheet SectionB
A1: --- Section B ---
A2: Name | B2: Marks
A3: Karan | B3: 88
A4: Priya | B4: 82
A5: Ravi | B5: 80

Sheet sectionC
A1: --- Section C ---
A2: Name | B2: Marks
A3: Priya | B3: 88
A4: Karan | B4: 92
A5: Ravi | B5: 81

Sheet sectionD
C1: Marks
B2: Day4_Task_6_Consolidate | C2: =sectionA!$B$3 -> 78
B3: Day4_Task_6_Consolidate | C3: =SectionB!$B$5 -> 80
B4: Day4_Task_6_Consolidate | C4: =sectionC!$B$5 -> 81
A5: Ravi | C5: =AVERAGE(C2:C4) -> 79.666667
B6: Day4_Task_6_Consolidate | C6: =sectionA!$B$4 -> 85
B7: Day4_Task_6_Consolidate | C7: =SectionB!$B$4 -> 82
B8: Day4_Task_6_Consolidate | C8: =sectionC!$B$3 -> 88
A9: Priya | C9: =AVERAGE(C6:C8) -> 85
B10: Day4_Task_6_Consolidate | C10: =sectionA!$B$5 -> 90
B11: Day4_Task_6_Consolidate | C11: =SectionB!$B$3 -> 88
B12: Day4_Task_6_Consolidate | C12: =sectionC!$B$4 -> 92
A13: Karan | C13: =AVERAGE(C10:C12) -> 90

Sheet Days
A1: --- Sheet Monday ---
A2: Student | B2: Present
A3: Anand | B3: 1
A4: Bala | B4: 1
A5: Devi | B5: 0
A6: --- Sheet Tuesday ---
A7: Student | B7: Present
A8: Devi | B8: 1
A9: Bala | B9: 1
A10: Anand | B10: 1
B12: Present
A13: Anand | B13: 2
A14: Bala | B14: 2
A15: Devi | B15: 1

Sheet Months
A1: --- Sheet April ---
A2: Item | B2: Sales
A3: Shoes | B3: 5000
A4: Shirts | B4: 7000
A5: Caps | B5: 3000
A6: --- Sheet May ---
A7: Item | B7: Sales
A8: Shoes | B8: 5000
A9: Shirts | B9: 7000
A10: Caps | B10: 3000
A11: --- Sheet June ---
A12: Item | B12: Sales
A13: Shoes | B13: 5000
A14: Shirts | B14: 7000
A15: Caps | B15: 3000
B17: Sales
A18: Shoes | B18: 15000
A19: Shirts | B19: 21000
A20: Caps | B20: 9000

Sheet departments
A1: --- Sheet HR ---
A2: Expense | B2: Amount
A3: Travel | B3: 10000
A4: Stationery | B4: 4000
A5: Snacks | B5: 3000
A6: --- Sheet IT ---
A7: Expense | B7: Amount
A8: Travel | B8: 10000
A9: Stationery | B9: 4000
A10: Snacks | B10: 3000
A11: --- Sheet Finance ---
A12: Expense | B12: Amount
A13: Travel | B13: 10000
A14: Stationery | B14: 4000
A15: Snacks | B15: 3000
A16: --- Sheet Admin ---
A17: Expense | B17: Amount
A18: Travel | B18: 10000
A19: Stationery | B19: 4000
A20: Snacks | B20: 3000
B22: Amount
A23: Travel | B23: 40000
A24: Stationery | B24: 16000
A25: Snacks | B25: 12000

Sheet order
A1: --- Sheet Online Orders ---
A2: Product | B2: Qty
A3: Mouse | B3: 40
A4: Keyboard | B4: 25
A5: Monitor | B5: 10
A6: --- Sheet Offline Orders ---
A7: Product | B7: Qty
A8: Keyboard | B8: 30
A9: Monitor | B9: 12
A10: Mouse | B10: 35
B12: Qty
A13: Mouse | B13: 75
A14: Keyboard | B14: 55
A15: Monitor | B15: 22

Sheet customer
A1: --- Sheet Day1 ---
A2: Customer | B2: count
A3: Ravi | B3: 1
A4: Priya | B4: 1
A5: Mani | B5: 1
A6: --- Sheet Day2 ---
A7: Customer | B7: count
A8: Priya | B8: 1
A9: Karan | B9: 1
A10: Ravi | B10: 1
B12: count
A13: Karan | B13: 1 | D13: I used sum and extra column as count because in consolidate count wont work for text
A14: Ravi | B14: 2
A15: Priya | B15: 2
A16: Mani | B16: 1

Sheet Test
A1: --- Sheet Test1 ---
A2: Name | B2: Marks
A3: Asha | B3: 80
A4: Ravi | B4: 70
A5: Karan | B5: 90
A6: --- Sheet Test2 ---
A7: Name | B7: Marks
A8: Asha | B8: 80
A9: Ravi | B9: 70
A10: Karan | B10: 90
A11: --- Sheet Test3 ---
A12: Name | B12: Marks
A13: Asha | B13: 80
A14: Ravi | B14: 70
A15: Karan | B15: 90
B17: Marks
A18: Asha | B18: 80
A19: Ravi | B19: 70
A20: Karan | B20: 90
